saturn_toolbox/Currency_conversion.py
saturn_toolbox/__init__.py
saturn_toolbox/cli.py
saturn_toolbox/ebayviewer.py
saturn_toolbox/randompassgen.py
saturn_toolbox/snkrs_el.py
saturn_toolbox/toolbox.py
saturn_toolbox/usmint_atc.py
saturn_toolbox-0.1.1.dist-info/LICENSE
saturn_toolbox-0.1.1.dist-info/METADATA
saturn_toolbox-0.1.1.dist-info/WHEEL
saturn_toolbox-0.1.1.dist-info/entry_points.txt
saturn_toolbox-0.1.1.dist-info/top_level.txt
saturn_toolbox-0.1.1.dist-info/RECORD
