Metadata-Version: 2.1
Name: saturn-toolbox
Version: 0.1.1
Summary: A toolbox for resekkers
Home-page: https://github.com/akavenus/saturn-toolbox
Author: Saturn Software
Author-email: saturn.dev@protonmail.com
License: UNKNOWN
Platform: UNKNOWN
Classifier: Programming Language :: Python :: 3
Classifier: License :: OSI Approved :: MIT License
Classifier: Operating System :: OS Independent
Requires-Python: >=3.6
